.DS_Store
hyperant/ui_hypercube.py
hyperant-2.7.data/scripts/hypercube.cpp
hyperant-2.7.data/scripts/hypercube.h
hyperant-2.7.data/scripts/run_hypercube
hyperant-2.7.dist-info/METADATA
hyperant-2.7.dist-info/WHEEL
hyperant-2.7.dist-info/entry_points.txt
hyperant-2.7.dist-info/top_level.txt
hyperant-2.7.dist-info/RECORD
