Metadata-Version: 2.1
Name: hyperant
Version: 2.7
Summary: BMC Research Programmer Technical Test - Ant on Cube
Home-page: https://github.com/v0rtex20k
Author: Victor Arsenescu
Author-email: victor.arsenescu@tufts.edu
License: MIT
Platform: UNKNOWN
Requires-Python: >3.5.2
Requires-Dist: typing
